{
  "sha": "86ceb7f292ff79138256525bb18bab2c6c80bd93",
  "hyperlinks": [
    {
      "url": {
        "url": "https://www.mediacityuk.co.uk/immersive-technologies-innovation-hub/",
        "published_date": null
      },
      "url_type": "Error: 'dict' object has no attribute 'decode'",
      "published_date": null,
      "weight": 0.5
    },
    {
      "url": {
        "url": "https://www.linkedin.com/company/dreamlabinstitute/?",
        "published_date": null
      },
      "url_type": "Error: 'dict' object has no attribute 'decode'",
      "published_date": null,
      "weight": 0.5
    },
    {
      "url": {
        "url": "https://github.com/flossverse",
        "published_date": null
      },
      "url_type": "Error: 'dict' object has no attribute 'decode'",
      "published_date": null,
      "weight": 0.5
    },
    {
      "url": {
        "url": "https://www.visionflow.info/680a51ea177aecc8cafb7003e146622b7ca13257/index.html#/graph",
        "published_date": null
      },
      "url_type": "Error: 'dict' object has no attribute 'decode'",
      "published_date": null,
      "weight": 0.5
    },
    {
      "url": {
        "url": "https://narrativegoldmine.com/#/graph\"",
        "published_date": null
      },
      "url_type": "Error: 'dict' object has no attribute 'decode'",
      "published_date": null,
      "weight": 0.5
    },
    {
      "url": {
        "url": "https://twitter.com/bentossell/status/1758235873433243950",
        "published_date": null
      },
      "url_type": "Error: 'dict' object has no attribute 'decode'",
      "published_date": null,
      "weight": 0.5
    },
    {
      "url": {
        "url": "https://twitter.com/bentossell/status/1758235873433243950}}",
        "published_date": null
      },
      "url_type": "Error: 'dict' object has no attribute 'decode'",
      "published_date": null,
      "weight": 0.5
    },
    {
      "url": {
        "url": "https://narrativegoldmine.com/#/graph\"",
        "published_date": null
      },
      "url_type": "Error: 'dict' object has no attribute 'decode'",
      "published_date": null,
      "weight": 0.5
    }
  ]
}